autohooks/plugins/pdoc/__init__.py
autohooks/plugins/pdoc/pdoc.py
autohooks_plugin_pdoc-0.1.2.dist-info/WHEEL
autohooks_plugin_pdoc-0.1.2.dist-info/METADATA
autohooks_plugin_pdoc-0.1.2.dist-info/RECORD
